django_logger_request/__init__.py
django_logger_request/django_logger_request.py
django_logger_request-0.0.1.dist-info/AUTHORS.rst
django_logger_request-0.0.1.dist-info/LICENSE
django_logger_request-0.0.1.dist-info/METADATA
django_logger_request-0.0.1.dist-info/WHEEL
django_logger_request-0.0.1.dist-info/top_level.txt
django_logger_request-0.0.1.dist-info/RECORD
