Metadata-Version: 2.1
Name: django_logger_request
Version: 0.0.1
Summary: Django middleware for logging requests and responses.
Author-email: Dinh Truong Quang <quangdinhvh2@gmail.com>
Maintainer-email: Dinh Truong Quang <quangdinhvh2@gmail.com>
License: GNU General Public License v3
Project-URL: bugs, https://github.com/banhmysuawx/django_logger_request/issues
Project-URL: changelog, https://github.com/banhmysuawx/django_logger_request/blob/master/changelog.md
Project-URL: homepage, https://github.com/banhmysuawx/django_logger_request
License-File: LICENSE
License-File: AUTHORS.rst
Provides-Extra: dev
Requires-Dist: coverage ; extra == 'dev'
Requires-Dist: mypy ; extra == 'dev'
Requires-Dist: pytest ; extra == 'dev'
Requires-Dist: ruff ; extra == 'dev'
